{
  "basement-hallway-2": {
    "camera_id": "basement-hallway-2",
    "camera_pts": [
      [
        92.1,
        93.4
      ],
      [
        58.2,
        28.3
      ],
      [
        40.0,
        28.3
      ],
      [
        5.0,
        89.0
      ]
    ],
    "floor_pts": [
      [
        24.5,
        24.3
      ],
      [
        34.7,
        31.2
      ],
      [
        29.3,
        36.5
      ],
      [
        18.2,
        28.4
      ]
    ],
    "floor_w": 1536,
    "floor_h": 1024,
    "label": "testing"
  }
}